sat_templates/VERSION
sat_templates/__init__.py
sat_templates/i18n/babel.ini
sat_templates/i18n/fr/LC_MESSAGES/sat.mo
sat_templates/i18n/fr/LC_MESSAGES/sat.po
sat_templates/i18n/sk/LC_MESSAGES/sat.mo
sat_templates/i18n/sk/LC_MESSAGES/sat.po
sat_templates/templates/bulma/_browser/__init__.py
sat_templates/templates/bulma/base/base.html
sat_templates/templates/bulma/blog/articles.html
sat_templates/templates/bulma/blog/atom.xml
sat_templates/templates/bulma/blog/comments_panel.html
sat_templates/templates/bulma/blog/discover.html
sat_templates/templates/bulma/blog/item.html
sat_templates/templates/bulma/blog/macros.html
sat_templates/templates/bulma/blog/publish.html
sat_templates/templates/bulma/chat/chat.html
sat_templates/templates/bulma/chat/message.html
sat_templates/templates/bulma/chat/select.html
sat_templates/templates/bulma/components/avatar.html
sat_templates/templates/bulma/components/block.html
sat_templates/templates/bulma/components/common.html
sat_templates/templates/bulma/components/images.html
sat_templates/templates/bulma/components/media_player.html
sat_templates/templates/bulma/components/menu_labels.html
sat_templates/templates/bulma/dialogs/confirm.html
sat_templates/templates/bulma/dialogs/macros.html
sat_templates/templates/bulma/dialogs/notification.html
sat_templates/templates/bulma/editor/tag.html
sat_templates/templates/bulma/editor/tags_editor.html
sat_templates/templates/bulma/embed/embed.html
sat_templates/templates/bulma/error/401.html
sat_templates/templates/bulma/error/403.html
sat_templates/templates/bulma/error/404.html
sat_templates/templates/bulma/error/base.html
sat_templates/templates/bulma/event/admin.html
sat_templates/templates/bulma/event/attendance.html
sat_templates/templates/bulma/event/counter.html
sat_templates/templates/bulma/event/create.html
sat_templates/templates/bulma/event/invitation.html
sat_templates/templates/bulma/event/overview.html
sat_templates/templates/bulma/file/discover.html
libervia_templates-0.8.0.dist-info/COPYING
libervia_templates-0.8.0.dist-info/METADATA
libervia_templates-0.8.0.dist-info/WHEEL
libervia_templates-0.8.0.dist-info/top_level.txt
libervia_templates-0.8.0.dist-info/RECORD
