Metadata-Version: 2.1
Name: libervia-templates
Version: 0.8.0
Summary: Templates for Libervia XMPP client
Home-page: https://salut-a-toi.org
Author: Association « Salut à Toi »
Author-email: contact@salut-a-toi.org
License: UNKNOWN
Platform: UNKNOWN
Classifier: Programming Language :: Python :: 3 :: Only
Classifier: Programming Language :: Python :: 3.7
Classifier: Programming Language :: Python :: 3.8
Classifier: Programming Language :: Python :: 3.9
Classifier: Development Status :: 5 - Production/Stable
Classifier: License :: OSI Approved :: GNU Affero General Public License v3 or later (AGPLv3+)
Requires-Python: >=3.7
License-File: COPYING
